nmtpytorch/__init__.py
nmtpytorch/cleanup.py
nmtpytorch/config.py
nmtpytorch/evaluator.py
nmtpytorch/logger.py
nmtpytorch/mainloop.py
nmtpytorch/monitor.py
nmtpytorch/optimizer.py
nmtpytorch/search.py
nmtpytorch/tester.py
nmtpytorch/translator.py
nmtpytorch/vocabulary.py
nmtpytorch/cocoeval/__init__.py
nmtpytorch/cocoeval/bleu/__init__.py
nmtpytorch/cocoeval/bleu/bleu.py
nmtpytorch/cocoeval/bleu/bleu_scorer.py
nmtpytorch/cocoeval/cider/__init__.py
nmtpytorch/cocoeval/cider/cider.py
nmtpytorch/cocoeval/cider/cider_scorer.py
nmtpytorch/cocoeval/meteor/__init__.py
nmtpytorch/cocoeval/meteor/meteor.py
nmtpytorch/cocoeval/rouge/__init__.py
nmtpytorch/cocoeval/rouge/rouge.py
nmtpytorch/datasets/__init__.py
nmtpytorch/datasets/collate.py
nmtpytorch/datasets/imagefolder.py
nmtpytorch/datasets/kaldi.py
nmtpytorch/datasets/label.py
nmtpytorch/datasets/multimodal.py
nmtpytorch/datasets/numpy.py
nmtpytorch/datasets/numpy_sequence.py
nmtpytorch/datasets/onehot.py
nmtpytorch/datasets/shelve.py
nmtpytorch/datasets/text.py
nmtpytorch/layers/__init__.py
nmtpytorch/layers/embedding.py
nmtpytorch/layers/ff.py
nmtpytorch/layers/flatten.py
nmtpytorch/layers/fusion.py
nmtpytorch/layers/max_margin.py
nmtpytorch/layers/rnninit.py
nmtpytorch/layers/seq_conv.py
nmtpytorch/layers/z.py
nmtpytorch/layers/z_att.py
nmtpytorch/layers/attention/__init__.py
nmtpytorch/layers/attention/co.py
nmtpytorch/layers/attention/dot.py
nmtpytorch/layers/attention/hierarchical.py
nmtpytorch/layers/attention/mhco.py
nmtpytorch/layers/attention/mlp.py
nmtpytorch/layers/decoders/__init__.py
nmtpytorch/layers/decoders/conditional.py
nmtpytorch/layers/decoders/conditionalmm.py
nmtpytorch/layers/decoders/multisourceconditional.py
nmtpytorch/layers/decoders/simplegru.py
nmtpytorch/layers/decoders/switchinggru.py
nmtpytorch/layers/decoders/vector.py
nmtpytorch/layers/decoders/xu.py
nmtpytorch/layers/encoders/__init__.py
nmtpytorch/layers/encoders/bilstmp.py
nmtpytorch/layers/encoders/feature.py
nmtpytorch-4.0.0.dist-info/LICENSE.md
nmtpytorch-4.0.0.dist-info/METADATA
nmtpytorch-4.0.0.dist-info/WHEEL
nmtpytorch-4.0.0.dist-info/top_level.txt
nmtpytorch-4.0.0.dist-info/RECORD
