Metadata-Version: 2.1
Name: nmtpytorch
Version: 4.0.0
Summary: Sequence-to-Sequence Framework in Pytorch
Home-page: https://github.com/lium-lst/nmtpytorch
Author: Ozan Caglayan
Author-email: ozan.caglayan@univ-lemans.fr
License: MIT
Project-URL: Wiki, https://github.com/lium-lst/nmtpytorch/wiki
Keywords: nmt neural-mt translation sequence-to-sequence deep-learning pytorch
Platform: UNKNOWN
Classifier: Intended Audience :: Science/Research
Classifier: Topic :: Scientific/Engineering
Classifier: License :: OSI Approved :: MIT License
Classifier: Programming Language :: Python :: 3 :: Only
Classifier: Programming Language :: Python :: 3.6
Classifier: Operating System :: POSIX
Requires-Python: ~=3.6
Requires-Dist: numpy
Requires-Dist: scipy
Requires-Dist: scikit-learn
Requires-Dist: tqdm
Requires-Dist: pillow
Requires-Dist: torch (==1.0.0)
Requires-Dist: torchvision (==0.2.1)
Requires-Dist: sacrebleu (>=1.2.9)
Requires-Dist: tensorboardX (==1.1)
Requires-Dist: editdistance (==0.4)
Requires-Dist: subword-nmt (==0.3.5)
